EMLMailReader/Content_Disposition.py
EMLMailReader/Content_Type.py
EMLMailReader/Custom_Exceptions.py
EMLMailReader/Enumerations.py
EMLMailReader/Mail_Address.py
EMLMailReader/Mail_Attachment.py
EMLMailReader/Mail_Reader.py
EMLMailReader/Processing_Logs.py
EMLMailReader/Rx_Mail_Message.py
EMLMailReader/Text_Encoding.py
EMLMailReader/__init__.py
emlmailreader-1.0.3.dist-info/licenses/LICENSE
emlmailreader-1.0.3.dist-info/METADATA
emlmailreader-1.0.3.dist-info/WHEEL
emlmailreader-1.0.3.dist-info/top_level.txt
emlmailreader-1.0.3.dist-info/RECORD
