Metadata-Version: 2.4
Name: emlmailreader
Version: 1.0.3
Summary: Parse EML file and export the information extracted as JSON.
Author-email: Mahesh Kumaar Balaji <maheshkumaar.balaji@outlook.com>
License: Copyright (c) 2018 The Python Packaging Authority
Project-URL: Homepage, https://github.com/citadelofcode/EMLMailReader
Project-URL: Issues, https://github.com/citadelofcode/EMLMailReader/issues
Keywords: email,reader,eml,parser
Classifier: License :: OSI Approved :: MIT License
Classifier: Programming Language :: Python
Classifier: Programming Language :: Python :: 3
Requires-Python: >=3.12
License-File: LICENSE
Dynamic: license-file
